{
        "properties": {
                "assigned_user_id": {
                        "type": "keyword"
                },
                "assigned_user_name": {
                        "type": "text",
                        "fielddata": true
                },
                "step_name": {
                        "type": "text",
                        "fielddata": true
                },
                "step_slug": {
                        "type": "keyword"
                },
                "cause_name": {
                        "type": "text",
                        "fielddata": true
                },
                "work_activity": {
                        "type": "text",
                        "fielddata": true
                },
                "alert_status": {
                        "type": "keyword"
                },
                "alert_submitter_id": {
                        "type": "keyword"
                },
                "alert_submitter_name": {
                        "type": "text",
                        "fielddata": true
                },
                "deadline_status": {
                        "type": "keyword"
                },
                "school_contact_name": {
                        "type": "text",
                        "fielddata": true
                },
                "place_is_quilombola": {
                        "type": "text",
                        "fielddata": true
                },
                "school_cep": {
                        "type": "text",
                        "fielddata": true
                },
                "parents_who_is_guardian": {
                        "type": "text",
                        "fielddata": true
                },
                "reinsertion_grade": {
                        "type": "text",
                        "fielddata": true
                },
                "school_name": {
                        "type": "text",
                        "fielddata": true
                },
                "school_last_status": {
                        "type": "text",
                        "fielddata": true
                },
                "school_last_id": {
                        "type": "keyword"
                },
                "handicapped_at_sus": {
                        "type": "integer"
                },
                "place_neighborhood": {
                        "type": "text",
                        "fielddata": true
                },
                "reinsertion_date": {
                        "format": "dateOptionalTime",
                        "type": "date"
                },
                "guardian_dob": {
                        "format": "dateOptionalTime",
                        "type": "date"
                },
                "father_name": {
                        "store": true,
                        "type": "text",
                        "fielddata": true
                },
                "race": {
                        "store": true,
                        "type": "text",
                        "fielddata": true
                },
                "is_working": {
                        "type": "integer"
                },
                "city_name": {
                        "store": true,
                        "type": "text",
                        "fielddata": true
                },
                "school_id": {
                        "type": "keyword"
                },
                "school_city_id": {
                        "type": "keyword"
                },
                "current_step_id": {
                        "type": "keyword"
                },
                "school_last_age": {
                        "type": "integer"
                },
                "age": {
                        "type": "integer"
                },
                "gender": {
                        "store": true,
                        "type": "text",
                        "fielddata": true
                },
                "cpf": {
                        "type": "keyword"
                },
                "parents_income": {
                        "type": "text",
                        "fielddata": true
                },
                "is_child_still_in_school": {
                        "type": "integer"
                },
                "parents_has_mother": {
                        "type": "integer"
                },
                "place_cep": {
                        "type": "keyword"
                },
                "school_address": {
                        "type": "text",
                        "fielddata": true
                },
                "guardian_race": {
                        "type": "text",
                        "fielddata": true
                },
                "current_step_type": {
                        "type": "keyword"
                },
                "guardian_name": {
                        "type": "text",
                        "fielddata": true
                },
                "place_kind": {
                        "type": "text",
                        "fielddata": true
                },
                "work_activity_other": {
                        "type": "text",
                        "fielddata": true
                },
                "work_is_paid": {
                        "type": "integer"
                },
                "updated_at": {
                        "store": true,
                        "format": "YYYY-MM-dd HH:mm:ss",
                        "type": "date"
                },
                "risk_level": {
                        "store": true,
                        "type": "text",
                        "fielddata": true
                },
                "alert_cause_id": {
                        "type": "keyword"
                },
                "parents_has_father": {
                        "type": "integer"
                },
                "school_city": {
                        "type": "text",
                        "fielddata": true
                },
                "guardian_job": {
                        "type": "text",
                        "fielddata": true
                },
                "parents_has_brother": {
                        "type": "integer"
                },
                "place_address": {
                        "type": "text",
                        "fielddata": true
                },
                "tenant_id": {
                        "store": true,
                        "type": "keyword"
                },
                "rg": {
                        "type": "keyword"
                },
                "school_last_name": {
                        "type": "text",
                        "fielddata": true
                },
                "current_case_id": {
                        "store": true,
                        "type": "keyword"
                },
                "observations": {
                        "type": "text",
                        "fielddata": true
                },
                "city_id": {
                        "store": true,
                        "type": "keyword"
                },
                "id": {
                        "store": true,
                        "type": "keyword"
                },
                "has_been_in_school": {
                        "type": "integer"
                },
                "report_index": {
                        "type": "long"
                },
                "actions_description": {
                        "type": "text",
                        "fielddata": true
                },
                "name": {
                        "store": true,
                        "type": "text",
                        "fielddata": true
                },
                "school_last_year": {
                        "type": "integer"
                },
                "created_at": {
                        "store": true,
                        "format": "YYYY-MM-dd HH:mm:ss",
                        "type": "date"
                },
                "place_reference": {
                        "type": "text",
                        "fielddata": true
                },
                "school_neighborhood": {
                        "type": "text",
                        "fielddata": true
                },
                "place_uf": {
                        "type": "text",
                        "fielddata": true
                },
                "school_uf": {
                        "type": "text",
                        "fielddata": true
                },
                "place_city": {
                        "type": "text",
                        "fielddata": true
                },
                "place_city_id": {
                        "type": "keyword"
                },
                "place_city_name": {
                        "type": "text",
                        "fielddata": true
                },
                "uf": {
                        "store": true,
                        "type": "text",
                        "fielddata": true
                },
                "assigned_uf": {
                        "store": true,
                        "type": "text",
                        "fielddata": true
                },
                "case_cause_ids": {
                        "type": "text",
                        "fielddata": true
                },
                "deleted_at": {
                        "store": true,
                        "format": "YYYY-MM-dd HH:mm:ss",
                        "type": "date"
                },
                "country_region": {
                        "store": true,
                        "type": "text",
                        "fielddata": true
                },
                "case_status": {
                        "store": true,
                        "type": "keyword"
                },
                "current_case": {
                        "properties": {
                                "case_cause_ids": {
                                        "store": true,
                                        "type": "keyword"
                                },
                                "assigned_user_id": {
                                        "store": true,
                                        "type": "keyword"
                                },
                                "current_step_type": {
                                        "store": true,
                                        "type": "text",
                                        "fielddata": true
                                },
                                "id": {
                                        "type": "keyword"
                                },
                                "created_by_user_id": {
                                        "store": true,
                                        "type": "keyword"
                                },
                                "current_step_id": {
                                        "store": true,
                                        "type": "keyword"
                                },
                                "updated_at": {
                                        "store": true,
                                        "format": "YYYY-MM-dd HH:mm:ss",
                                        "type": "date"
                                },
                                "risk_level": {
                                        "store": true,
                                        "type": "text",
                                        "fielddata": true
                                },
                                "linked_steps": {
                                        "properties": {
                                                "id": {
                                                        "type": "keyword"
                                                },
                                                "index": {
                                                        "type": "long",
                                                        "index": "false"
                                                },
                                                "next": {
                                                        "properties": {
                                                                "index": {
                                                                        "type": "long",
                                                                        "index": "false"
                                                                },
                                                                "type": {
                                                                        "type": "keyword"
                                                                }
                                                        }
                                                },
                                                "type": {
                                                        "type": "keyword"
                                                }
                                        }
                                },
                                "alert_cause_id": {
                                        "store": true,
                                        "type": "text",
                                        "fielddata": true
                                },
                                "name": {
                                        "store": true,
                                        "type": "text",
                                        "fielddata": true
                                },
                                "child_id": {
                                        "type": "keyword"
                                },
                                "created_at": {
                                        "store": true,
                                        "format": "YYYY-MM-dd HH:mm:ss",
                                        "type": "date"
                                },
                                "case_status": {
                                        "store": true,
                                        "type": "text",
                                        "fielddata": true
                                },
                                "is_current": {
                                        "type": "integer"
                                },
                                "enrolled_at": {
                                        "store": true,
                                        "format": "dateOptionalTime",
                                        "type": "date"
                                },
                                "assigned_group_id": {
                                        "store": true,
                                        "type": "keyword"
                                },
                                "cancel_reason": {
                                        "store": true,
                                        "type": "text",
                                        "fielddata": true
                                }
                        }
                },
                "work_weekly_hours": {
                        "type": "integer"
                },
                "school_last_grade": {
                        "type": "text",
                        "fielddata": true
                },
                "evasion_reason": {
                        "type": "text",
                        "fielddata": true
                },
                "handicapped_reason_not_enrolled": {
                        "type": "text",
                        "fielddata": true
                },
                "nis": {
                        "type": "keyword"
                },
                "dob": {
                        "store": true,
                        "format": "dateOptionalTime",
                        "type": "date"
                },
                "mother_name": {
                        "store": true,
                        "type": "text",
                        "fielddata": true
                },
                "guardian_schooling": {
                        "type": "text",
                        "fielddata": true
                },
                "child_status": {
                        "store": true,
                        "type": "text",
                        "fielddata": true
                },
                "school_last_address": {
                        "type": "text",
                        "fielddata": true
                },
                "reason_not_enrolled": {
                        "type": "text",
                        "fielddata": true
                }
        }
}
